pyfm2d-0.1.6.dist-info/RECORD
pyfm2d-0.1.6.dist-info/WHEEL
pyfm2d-0.1.6.dist-info/METADATA
pyfm2d-0.1.6.dist-info/licenses/LICENSE
pyfm2d/wavetracker.py
pyfm2d/version.py
pyfm2d/__init__.py
pyfm2d/libfm2d.cpython-311-darwin.so
pyfm2d/bases.py
pyfm2d/fastmarching.py
pyfm2d/.dylibs/libgfortran.5.dylib
pyfm2d/.dylibs/libquadmath.0.dylib
pyfm2d/.dylibs/libgcc_s.1.1.dylib
