Metadata-Version: 2.2
Name: pyfm2d
Version: 0.1.6
Requires-Python: >=3.9
Requires-Dist: cartopy>=0.2.3
Requires-Dist: matplotlib>=3.9.4
Requires-Dist: numpy>=2.0.2
Requires-Dist: pyrr>=0.10.3
Requires-Dist: scipy>=1.13.1
Requires-Dist: tqdm>=4.67.1
Provides-Extra: notebooks
Requires-Dist: jupyterlab>=4.3.4; extra == "notebooks"
